setup.py
NekoCAS/__init__.py
NekoCAS.egg-info/PKG-INFO
NekoCAS.egg-info/SOURCES.txt
NekoCAS.egg-info/dependency_links.txt
NekoCAS.egg-info/requires.txt
NekoCAS.egg-info/top_level.txt