Metadata-Version: 1.0
Name: NekoCAS
Version: 0.3
Summary: NekoCAS SDK for Python
Home-page: https://github.com/NekoWheel/NekoCAS_Python_SDK
Author: E99p1ant
Author-email: i@github.red
License: UNKNOWN
Platform: any
